mb_base1/__init__.py
mb_base1/app.py
mb_base1/config.py
mb_base1/db.py
mb_base1/errors.py
mb_base1/jinja.py
mb_base1/json_encoder.py
mb_base1/models.py
mb_base1/server.py
mb_base1/telegram.py
mb_base1/utils.py
mb_base1/routers/__init__.py
mb_base1/routers/base_ui_router.py
mb_base1/routers/dconfig_router.py
mb_base1/routers/dlog_router.py
mb_base1/routers/dvalue_router.py
mb_base1/routers/system_router.py
mb_base1/services/__init__.py
mb_base1/services/base.py
mb_base1/services/dconfig_service.py
mb_base1/services/dvalue_service.py
mb_base1/services/system_service.py
mb_base1/static/bootstrap.bundle.min.js
mb_base1/static/bootstrap.min.css
mb_base1/static/favicon.ico
mb_base1/static/mb-base1.css
mb_base1/static/sortable.css
mb_base1/static/sortable.min.js
mb_base1/templates/dconfig.j2
mb_base1/templates/dlogs.j2
mb_base1/templates/dvalue.j2
mb_base1/templates/login.j2
mb_base1/templates/system.j2
mb_base1/templates/update_dconfig.j2
mb_base1/templates/update_dconfig_multiline.j2
mb_base1/templates/update_dvalue.j2
mb_base1/templates/inc/base.j2
mb_base1/templates/inc/macros/dropdown.j2
mb_base1/templates/inc/macros/inline_form.j2
mb_base1/templates/inc/macros/simple_form.j2
mb_base1/templates/inc/macros/table_form.j2
mb_base1-0.4.19.dist-info/METADATA
mb_base1-0.4.19.dist-info/WHEEL
mb_base1-0.4.19.dist-info/top_level.txt
mb_base1-0.4.19.dist-info/RECORD
