Metadata-Version: 2.1
Name: mb-base1
Version: 0.4.19
Requires-Python: >=3.10
Requires-Dist: fastapi (==0.78.0)
Requires-Dist: Jinja2 (==3.1.2)
Requires-Dist: aiofiles (==0.8.0)
Requires-Dist: itsdangerous (==2.1.2)
Requires-Dist: WTForms (==3.0.1)
Requires-Dist: python-multipart (==0.0.5)
Requires-Dist: uvicorn[standard] (==0.18.2)
Requires-Dist: gunicorn (==20.1.0)
Requires-Dist: pyTelegramBotAPI (==4.6.0)
Requires-Dist: mb-std (~=0.4.7)
Provides-Extra: dev
Requires-Dist: pytest (==7.1.2) ; extra == 'dev'
Requires-Dist: pre-commit (==2.19.0) ; extra == 'dev'
Requires-Dist: wheel (==0.37.1) ; extra == 'dev'
Requires-Dist: twine (==4.0.1) ; extra == 'dev'
Requires-Dist: pip-audit (==2.4.0) ; extra == 'dev'
